protections/__init__.py
protections/protections.py
protections_v1-0.2.7.dist-info/METADATA
protections_v1-0.2.7.dist-info/WHEEL
protections_v1-0.2.7.dist-info/entry_points.txt
protections_v1-0.2.7.dist-info/top_level.txt
protections_v1-0.2.7.dist-info/RECORD
